<?xml version="1.0"?>
<Results version="1.0">
<ReportNode type="testrun">
<ReportNode type="Iteration">
<ReportNode type="Action">
<ReportNode type="User">
<Data>
    <Name>Returning values from FL</Name>
    <Description>Result: &lt;&lt;returned from FL&gt;&gt;</Description>
    <StartTime>2021-11-10 14:42:57</StartTime>
    <Result>Passed</Result>
    <Extension>
      <IconKey>2aa73896e3714bb2b6c0eff2a4f551ad</IconKey>
      <IsPlainTextNodeName>True</IsPlainTextNodeName>
      <IsPlainTextStepInfo>True</IsPlainTextStepInfo>
    </Extension>
  </Data>
</ReportNode>
<Data>
    <Name>Action1</Name>
    <Description />
    <StartTime>2021-11-10 14:42:57</StartTime>
    <Duration>0</Duration>
    <Result>Passed</Result>
    <InputParameters />
    <Extension>
      <IconKey>8d8cb944cce440c491e824137054495b</IconKey>
      <IsPlainTextNodeName>True</IsPlainTextNodeName>
    </Extension>
  </Data>
</ReportNode>
<Data>
    <Name>Action0</Name>
    <Description />
    <StartTime>2021-11-10 14:42:57</StartTime>
    <Duration>0</Duration>
    <Result>Passed</Result>
    <Extension>
      <IconKey>cb88810dfc864c68b316cab78ddba04b</IconKey>
      <IsPlainTextNodeName>True</IsPlainTextNodeName>
    </Extension>
    <Index>1</Index>
    <TestedApplications />
  </Data>
</ReportNode>
<Data>
    <Name>TestFuncLibCase</Name>
    <ToolName>Micro Focus UFT One</ToolName>
    <ToolVersion>0</ToolVersion>
    <ToolVersionStringLiteral>16.0.0</ToolVersionStringLiteral>
    <Description />
    <StartTime>2021-11-10 14:42:52</StartTime>
    <Duration>5</Duration>
    <Result>Passed</Result>
    <InputParameters />
    <Extension>
      <IconKey>751e4e2d35e8442e94a71cba132660f0</IconKey>
      <IsPlainTextNodeName>True</IsPlainTextNodeName>
    </Extension>
    <Environment>
      <Timezone>+02:00:00</Timezone>
      <Locale>English (United States)</Locale>
      <User>swinfra\_ft_auto</User>
      <CpuInfo>Intel(R) Xeon(R) CPU E5-2640 v3 @ 2.60GHz</CpuInfo>
      <NumberOfCores>2</NumberOfCores>
      <TotalMemory>4095</TotalMemory>
      <HostName>swinfra.net\MYD-HVM04191</HostName>
      <OSInfo>Windows 10</OSInfo>
    </Environment>
    <TestedApplications />
    <Links>
      <Link type="DataTable" reference="Default.xlsx" displayname="Default Data Table" />
    </Links>
  </Data>
</ReportNode>
<GeneralInfo>
    <ResultName>Res1</ResultName>
    <RunStartTime>2021-11-10 14:42:52</RunStartTime>
    <Timezone>+02:00:00</Timezone>
    <OrchestrationToolName>Micro Focus UFT One</OrchestrationToolName>
    <OrchestrationToolVersion>0</OrchestrationToolVersion>
    <OrchestrationToolVersionStringLiteral>16.0.0</OrchestrationToolVersionStringLiteral>
  </GeneralInfo>
</Results>